MANIFEST.in
README.rst
interpy.pth
setup.py
interpy/__init__.py
interpy/six.py
interpy.egg-info/PKG-INFO
interpy.egg-info/SOURCES.txt
interpy.egg-info/dependency_links.txt
interpy.egg-info/top_level.txt
interpy/codec/__init__.py
interpy/codec/register.py
interpy/codec/tokenizer.py
interpy/codec/utils.py