Metadata-Version: 1.1
Name: interpy
Version: 1.1
Summary: Interpy extends Python to support Ruby like string interpolation #{}.
Home-page: http://github.com/syrusakbary/interpy
Author: Syrus Akbary
Author-email: me@syrusakbary.com
License: MIT
Download-URL: git@github.com:syrusakbary/interpy.git
Keywords: python string interpolation interpolate ruby codec
Platform: UNKNOWN
Classifier: Intended Audience :: Developers
Classifier: License :: OSI Approved :: MIT License
Classifier: Operating System :: OS Independent
Classifier: Programming Language :: Python
Classifier: Programming Language :: Python :: 2
Classifier: Programming Language :: Python :: 2.7
Classifier: Programming Language :: Python :: 3
Classifier: Programming Language :: Python :: 3.2
Classifier: Programming Language :: Python :: 3.3
Classifier: Topic :: Software Development :: Libraries :: Python Modules
